{
  "data": [
    {
      "id": "R_kgDOIrKTPg",
      "name": "Password-Manager-App",
      "createdAt": "2022-12-25T19:48:10Z",
      "url": "https://github.com/iabhi4/Password-Manager-App",
      "description": "A simple password manager app which stores the encrypted passwords locally in your phone storage. OWN YOUR PASSWORDS",
      "isFork": false,
      "languages": [
        {
          "name": "Ruby",
          "iconifyClass": "logos:ruby"
        },
        {
          "name": "HTML",
          "iconifyClass": "logos-html-5"
        }
      ]
    },
    {
      "id": "R_kgDOLy49Vg",
      "name": "Blockchain-Based-Voting-System",
      "createdAt": "2024-04-24T23:56:40Z",
      "url": "https://github.com/iabhi4/Blockchain-Based-Voting-System",
      "description": "Online Voting using Ethereum smart contracts",
      "isFork": false,
      "languages": [
        {
          "name": "JavaScript",
          "iconifyClass": "logos-javascript"
        },
        {
          "name": "HTML",
          "iconifyClass": "logos-html-5"
        },
        {
          "name": "CSS",
          "iconifyClass": "logos-css-3"
        }
      ]
    },
    {
      "id": "R_kgDOMB9YhA",
      "name": "Class-Enroll-Ease",
      "createdAt": "2024-05-29T00:37:03Z",
      "url": "https://github.com/iabhi4/Class-Enroll-Ease",
      "description": "Backend infrastructure for a comprehensive service for managing semester classes, including enrollment, de-enrollment, waitlisting, and administrative tasks for instructors and registrars including role based authentication and push notification services.",
      "isFork": false,
      "languages": [
        {
          "name": "Python",
          "iconifyClass": "logos-python"
        },
        {
          "name": "Shell",
          "iconifyClass": "simple-icons:shell"
        }
      ]
    },
    {
      "id": "R_kgDOMWN5WA",
      "name": "iabhi4.github.io",
      "createdAt": "2024-07-14T16:33:42Z",
      "url": "https://github.com/iabhi4/iabhi4.github.io",
      "description": "Developer portfolio",
      "isFork": false,
      "languages": [
        {
          "name": "HTML",
          "iconifyClass": "logos-html-5"
        }
      ]
    }
  ]
}
